qvibe/__init__.py
qvibe/__main__.py
qvibe/accelerometer.py
qvibe/app.py
qvibe/config.py
qvibe/handler.py
qvibe/i2cio.py
qvibe/interface.py
qvibe/mpu6050.py
qvibe/test/__init__.py
qvibe/test/test_handler.py
qvibe/test/test_mpu6050.py
qvibe_recorder-0.1.0.dist-info/LICENSE
qvibe_recorder-0.1.0.dist-info/METADATA
qvibe_recorder-0.1.0.dist-info/WHEEL
qvibe_recorder-0.1.0.dist-info/entry_points.txt
qvibe_recorder-0.1.0.dist-info/top_level.txt
qvibe_recorder-0.1.0.dist-info/RECORD
