Metadata-Version: 2.1
Name: qvibe-recorder
Version: 0.1.0
Summary: Bridges data to/from a mpu6050 to a tcp socket
Home-page: http://github.com/3ll3d00d/qvibe-recorder
Author: Matt Khan
Author-email: mattkhan+qvibe-recorder@gmail.com
License: MIT License
Requires-Dist: smbus2
Requires-Dist: pyyaml
Requires-Dist: twisted
